{
  "AMZN": {
    "history": "2025-06-22T20:11:07.328Z"
  },
  "NVDA": {
    "history": "2025-06-22T20:11:07.668Z"
  },
  "BABA": {
    "history": "2025-06-22T20:11:07.974Z"
  },
  "GOOGL": {
    "history": "2025-06-22T20:11:03.920Z"
  },
  "JPM": {
    "history": "2025-06-22T20:11:08.121Z"
  },
  "KO": {
    "history": "2025-06-22T20:11:08.472Z"
  },
  "PFE": {
    "history": "2025-06-22T20:11:08.581Z"
  },
  "MSFT": {
    "history": "2025-06-22T20:11:07.205Z"
  },
  "AAPL": {
    "history": "2025-06-22T20:11:09.392Z"
  },
  "TSLA": {
    "history": "2025-06-22T20:11:02.570Z"
  }
}